viablimp/__init__.py
viablimp-0.1.dist-info/METADATA
viablimp-0.1.dist-info/RECORD
viablimp-0.1.dist-info/WHEEL
viablimp-0.1.dist-info/top_level.txt
