Metadata-Version: 2.1
Name: viablimp
Version: 0.1
Summary: logging messages by facebook bot to your account
Home-page: http://github.com/theflyingmantis/facebooklogger
Author: Abhinav Rai
Author-email: rai.1@iitj.ac.in
License: MIT
Platform: UNKNOWN
Requires-Dist: requests
